Metadata-Version: 2.4
Name: ingenannot
Version: 0.0.17
Summary: InGenAnnot: Inspection of Gene Annotation
Author-email: Nicolas Lapalu <nicolas.lapalu@inrae.fr>
License-Expression: GPL-3.0
Project-URL: Homepage, https://forgemia.inra.fr/bioger/ingenannot
Classifier: Intended Audience :: Developers
Classifier: Operating System :: POSIX
Classifier: Operating System :: Unix
Classifier: Topic :: Scientific/Engineering
Classifier: Programming Language :: Python :: 3.7
Requires-Python: >=3.7
License-File: LICENSE
Requires-Dist: str2bool
Requires-Dist: numpy
Requires-Dist: pysam
Requires-Dist: matplotlib
Requires-Dist: pandas
Requires-Dist: upsetplot
Requires-Dist: seaborn
Requires-Dist: scikit-bio
Dynamic: license-file
